docketalarm_api/__init__.py
docketalarm_api/api_client.py
docketalarm_api-1.1.3.dist-info/METADATA
docketalarm_api-1.1.3.dist-info/WHEEL
docketalarm_api-1.1.3.dist-info/RECORD
