Metadata-Version: 2.1
Name: docketalarm_api
Version: 1.1.3
Summary: Wrapper to interact with DocketAlarm API
Home-page: https://www.docketalarm.com/dockets/
Author: Ezequiel Ghiena
Author-email: ezequiel.ghiena@vlex.com
Requires-Python: >=3.8,<4.0
Classifier: Programming Language :: Python :: 3
Classifier: Programming Language :: Python :: 3.8
Classifier: Programming Language :: Python :: 3.9
Classifier: Programming Language :: Python :: 3.10
Classifier: Programming Language :: Python :: 3.11
Classifier: Programming Language :: Python :: 3.12
Classifier: Programming Language :: Python :: 3.13
Requires-Dist: requests (>=2.26.0,<3.0.0)
Project-URL: Documentation, https://www.docketalarm.com/api/v1/
